parsex-0.1.1.dist-info/METADATA
parsex-0.1.1.dist-info/WHEEL
parsex/__init__.py
parsex/api.py
parsex/clearhtml.py
parsex/datetime.py
parsex/jsobject.py
parsex/py.typed
parsex/structdata.py
parsex/text.py
parsex/url.py
parsex-0.1.1.dist-info/RECORD
